gists_gone/__init__.py
gists_gone/gists_gone.py
gists_gone-0.0.2.dist-info/LICENSE
gists_gone-0.0.2.dist-info/METADATA
gists_gone-0.0.2.dist-info/WHEEL
gists_gone-0.0.2.dist-info/entry_points.txt
gists_gone-0.0.2.dist-info/top_level.txt
gists_gone-0.0.2.dist-info/RECORD
