Metadata-Version: 2.1
Name: gists-gone
Version: 0.0.2
Summary: A CLI that gives you more granular control over bulk deletion of your Github gists.
Author-email: Ben Nour <author@example.com>
Maintainer-email: Ben Nour <hello@ben-nour.com>
License: MIT License
Project-URL: homepage, https://github.com/ben-n93/gists-gone/
Project-URL: repository, https://github.com/ben-n93/gists-gone
Keywords: gists,Github
Classifier: Environment :: Console
Classifier: Intended Audience :: Developers
Classifier: License :: OSI Approved :: MIT License
Classifier: Programming Language :: Python :: 3
Classifier: Programming Language :: Python :: 3.8
Classifier: Programming Language :: Python :: 3.9
Classifier: Programming Language :: Python :: 3.10
Classifier: Programming Language :: Python :: 3.11
Classifier: Programming Language :: Python :: 3.12
Requires-Python: >=3.8
License-File: LICENSE
Requires-Dist: alive-progress
Requires-Dist: requests
Requires-Dist: rich
